azure/__init__.py
azure/devops/__init__.py
azure/devops/_file_cache.py
azure/devops/_models.py
azure/devops/client.py
azure/devops/client_configuration.py
azure/devops/connection.py
azure/devops/credentials.py
azure/devops/exceptions.py
azure/devops/version.py
azure/devops/issue_tests/__init__.py
azure/devops/issue_tests/test_issue_268.py
azure/devops/released/__init__.py
azure/devops/released/client_factory.py
azure/devops/released/accounts/__init__.py
azure/devops/released/accounts/accounts_client.py
azure/devops/released/build/__init__.py
azure/devops/released/build/build_client.py
azure/devops/released/cix/__init__.py
azure/devops/released/cix/cix_client.py
azure/devops/released/core/__init__.py
azure/devops/released/core/core_client.py
azure/devops/released/elastic/__init__.py
azure/devops/released/elastic/elastic_client.py
azure/devops/released/feed/__init__.py
azure/devops/released/feed/feed_client.py
azure/devops/released/git/__init__.py
azure/devops/released/git/git_client.py
azure/devops/released/git/git_client_base.py
azure/devops/released/graph/__init__.py
azure/devops/released/graph/graph_client.py
azure/devops/released/identity/__init__.py
azure/devops/released/identity/identity_client.py
azure/devops/released/member_entitlement_management/__init__.py
azure/devops/released/member_entitlement_management/member_entitlement_management_client.py
azure/devops/released/notification/__init__.py
azure/devops/released/notification/notification_client.py
azure/devops/released/npm/__init__.py
azure/devops/released/npm/npm_client.py
azure/devops/released/nuget/__init__.py
azure/devops/released/nuget/nuget_client.py
azure/devops/released/operations/__init__.py
azure/devops/released/operations/operations_client.py
azure/devops/released/pipelines/__init__.py
azure/devops/released/pipelines/pipelines_client.py
azure/devops/released/policy/__init__.py
azure/devops/released/policy/policy_client.py
azure/devops/released/profile/__init__.py
azure_devops-7.1.0b3.dist-info/LICENSE.txt
azure_devops-7.1.0b3.dist-info/METADATA
azure_devops-7.1.0b3.dist-info/WHEEL
azure_devops-7.1.0b3.dist-info/top_level.txt
azure_devops-7.1.0b3.dist-info/RECORD
