Metadata-Version: 2.1
Name: azure-devops
Version: 7.1.0b3
Summary: Python wrapper around the Azure DevOps 7.x APIs
Home-page: https://github.com/microsoft/azure-devops-python-api
Author: Microsoft Corporation
License: MIT
Keywords: Microsoft,VSTS,Team Services,SDK,AzureTfs,AzureDevOps,DevOps
Classifier: Development Status :: 4 - Beta
Classifier: Intended Audience :: Developers
Classifier: Intended Audience :: System Administrators
Classifier: Programming Language :: Python
Classifier: Programming Language :: Python :: 3
Classifier: Programming Language :: Python :: 3.7
Classifier: Programming Language :: Python :: 3.8
Classifier: Programming Language :: Python :: 3.9
Classifier: Programming Language :: Python :: 3.10
Classifier: Programming Language :: Python :: 3.11
Classifier: License :: OSI Approved :: MIT License
Requires-Python: >=3.7
License-File: LICENSE.txt
